pyftype/__init__.py
pyftype/cli.py
pyftype/modules/__init__.py
pyftype/modules/android.py
pyftype/modules/application.py
pyftype/modules/archive.py
pyftype/modules/audio.py
pyftype/modules/font.py
pyftype/modules/image.py
pyftype/modules/isobmff.py
pyftype/modules/video.py
pyftype/utils.py
pyftype-1.2.3.dist-info/entry_points.txt
pyftype-1.2.3.dist-info/LICENSE
pyftype-1.2.3.dist-info/WHEEL
pyftype-1.2.3.dist-info/METADATA
pyftype-1.2.3.dist-info/RECORD
