Metadata-Version: 2.1
Name: pyftype
Version: 1.2.3
Summary: 类型检测
Home-page: https://gitee.com/kin9-0rz/pyftype
License: MIT
Author: kin9-0rz
Author-email: kin9-0rz@outlook.com
Requires-Python: >=3.7,<3.11
Classifier: Development Status :: 5 - Production/Stable
Classifier: License :: OSI Approved :: MIT License
Classifier: Natural Language :: Chinese (Simplified)
Classifier: Programming Language :: Python :: 3
Classifier: Programming Language :: Python :: 3.10
Classifier: Programming Language :: Python :: 3.7
Classifier: Programming Language :: Python :: 3.8
Classifier: Programming Language :: Python :: 3.9
Classifier: Topic :: Software Development :: Libraries :: Python Modules
Classifier: Topic :: Utilities
Project-URL: Repository, https://gitee.com/kin9-0rz/pyftype
